{
    "NESound" : [
        {
                 "title" : "101ocean"
                 "imagename" : "101ocean"
                 "audioname" : "101ocean"
        },
      ],
    "AESound" : [
        {
                 "title" : "202gate1"
                 "imagename" : "202gate1"
                 "audioname" : "202gate1"
        },
    
        {
                 "title" : "203octopus1"
                 "imagename" : "203octopus1"
                 "audioname" : "203octopus1"
        },
                 
        {
                 "title" : "203octopus2"
                 "imagename" : "203octopus2"
                 "audioname" : "203octopus2"
        },
                 
        {
                 "title" : "204fountain1"
                 "imagename" : "204fountain1"
                 "audioname" : "204fountain1"
        },
                 
        {
                 "title" : "204fountain2"
                 "imagename" : "204fountain2"
                 "audioname" : "204fountain2"
        },
                 
        {
                 "title" : "205ventilation1"
                 "imagename" : "205ventilation1"
                 "audioname" : "205ventilation1"
        },
                 
        {
                 "title" : "205ventilation2"
                 "imagename" : "205ventilation2"
                 "audioname" : "205ventilation2"
        },
                 
        {
                 "title" : "208escalator1"
                 "imagename" : "208escalator1"
                 "audioname" : "208escalator1"
        },
                 
        {
                 "title" : "208escalator2"
                 "imagename" : "208escalator2"
                 "audioname" : "208escalator2"
        },
                 
        {
                 "title" : "209trafficlightblink"
                 "imagename" : "209trafficlightblink"
                 "audioname" : "209trafficlightblink"
        },
                 
        {
                 "title" : "209trafficlightgreen"
                 "imagename" : "209trafficlightgreen"
                 "audioname" : "209trafficlightgreen"
        },
                 
        {
                 "title" : "209trafficlightred"
                 "imagename" : "209trafficlightred"
                 "audioname" : "209trafficlightred"
        },
                 
        {
                 "title" : "210announcement1esccanto"
                 "imagename" : "210announcement1esccanto"
                 "audioname" : "210announcement1esccanto"
        },
                 
        {
                 "title" : "210announcement2esceng"
                 "imagename" : "210announcement2esceng"
                 "audioname" : "210announcement2esceng"
        },
                 
        {
                 "title" : "210announcement3wetfloor"
                 "imagename" : "210announcement3wetfloor"
                 "audioname" : "210announcement3wetfloor"
        },
                 
        {
                 "title" : "210announcement4escedge"
                 "imagename" : "210announcement4escedge"
                 "audioname" : "210announcement4escedge"
        },
                 
        {
                 "title" : "211gatebuzzer1carpark"
                 "imagename" : "211gatebuzzer1carpark"
                 "audioname" : "211gatebuzzer1carpark"
        },
                 
    ],
    
    
     "NISound" : [
                  
        {
                 "title" : "301bird1"
                 "imagename" : "301bird1"
                 "audioname" : "301bird1"
        },
                 
        {
                 "title" : "301bird2"
                 "imagename" : "301bird2"
                 "audioname" : "301bird2"
        },
                 
        {
                 "title" : "301bird3"
                 "imagename" : "301bird3"
                 "audioname" : "301bird3"
        },
                 
        {
                 "title" : "302cicada1"
                 "imagename" : "302cicada1"
                 "audioname" : "302cicada1"
        },
                 
        {
                 "title" : "302cicada2"
                 "imagename" : "302cicada2"
                 "audioname" : "302cicada2"
        },
                 
        {
                 "title" : "304chatter1footbridge"
                 "imagename" : "304chatter1footbridge"
                 "audioname" : "304chatter1footbridge"
        },
                 
        {
                 "title" : "304chatter2alexander"
                 "imagename" : "304chatter2alexander"
                 "audioname" : "304chatter2alexander"
        },
                 
        {
                 "title" : "304chatter3diner"
                 "imagename" : "304chatter3diner"
                 "audioname" : "304chatter3diner"
        },
                 
        {
                 "title" : "304chattercanto1"
                 "imagename" : "304chattercanto1"
                 "audioname" : "304chattercanto1"
        },
                 
        {
                 "title" : "304chattercanto2"
                 "imagename" : "304chattercanto2"
                 "audioname" : "304chattercanto2"
        },
                 
        {
                 "title" : "304chattercanto3"
                 "imagename" : "304chattercanto3"
                 "audioname" : "304chattercanto3"
        },
                 
        {
                 "title" : "304chattercanto4"
                 "imagename" : "304chattercanto4"
                 "audioname" : "304chattercanto4"
        },
                 
        {
                 "title" : "304chattercanto5"
                 "imagename" : "304chattercanto5"
                 "audioname" : "304chattercanto5"
        },
                 
        {
                 "title" : "304chattercanto6"
                 "imagename" : "304chattercanto6"
                 "audioname" : "304chattercanto6"
        },
                 
        {
                 "title" : "304chattereng1jardine"
                 "imagename" : "304chattereng1jardine"
                 "audioname" : "304chattereng1jardine"
        },
                 
        {
                 "title" : "304chattereng2subway"
                 "imagename" : "304chattereng2subway"
                 "audioname" : "304chattereng2subway"
        },
                 
        {
                 "title" : "304chatterkorean1"
                 "imagename" : "304chatterkorean1"
                 "audioname" : "304chatterkorean1"
        },
                 
        {
                 "title" : "304chatterlaugh"
                 "imagename" : "304chatterlaugh"
                 "audioname" : "304chatterlaugh"
        },
                 
        {
                 "title" : "304chatterpth1"
                 "imagename" : "304chatterpth1"
                 "audioname" : "304chatterpth1"
        },
                 
        {
                 "title" : "304chatterpth2"
                 "imagename" : "304chatterpth2"
                 "audioname" : "304chatterpth2"
        },
                 
        {
                 "title" : "304chattertagalog1"
                 "imagename" : "304chattertagalog1"
                 "audioname" : "304chattertagalog1"
        },
                 
        {
                 "title" : "304chattertagalog2"
                 "imagename" : "304chattertagalog2"
                 "audioname" : "304chattertagalog2"
        },
           
    ],
    
    "AISound" : [
                  
        {
                 "title" : "402cutleries1"
                 "imagename" : "402cutleries1"
                 "audioname" : "402cutleries1"
        },
                 
        {
                 "title" : "402cutleries2"
                 "imagename" : "402cutleries2"
                 "audioname" : "402cutleries2"
        },
                 
        {
                 "title" : "405engine1bus"
                 "imagename" : "405engine1bus"
                 "audioname" : "405engine1bus"
        },
                 
        {
                 "title" : "405engine2"
                 "imagename" : "405engine2"
                 "audioname" : "405engine2"
        },
                 
        {
                 "title" : "405engine3shuttle"
                 "imagename" : "405engine3shuttle"
                 "audioname" : "405engine3shuttle"
        },
                 
        {
                 "title" : "405engine4minivan"
                 "imagename" : "405engine4minivan"
                 "audioname" : "405engine4minivan"
        },
                 
        {
                 "title" : "405engine5boat"
                 "imagename" : "405engine5boat"
                 "audioname" : "405engine5boat"
        },
            
        {
                 "title" : "405engine6boat"
                 "imagename" : "405engine6boat"
                 "audioname" : "405engine6boat"
        },
                 
        {
                 "title" : "405engine7"
                 "imagename" : "405engine7"
                 "audioname" : "405engine7"
        },
            
        {
                 "title" : "406washfloor"
                 "imagename" : "406washfloor"
                 "audioname" : "406washfloor"
        },
                 
        {
                 "title" : "407buskingfb1dream"
                 "imagename" : "407buskingfb1dream"
                 "audioname" : "407buskingfb1dream"
        },
                 
        {
                 "title" : "407buskingfb2harmonica"
                 "imagename" : "407buskingfb2harmonica"
                 "audioname" : "407buskingfb2harmonica"
        },
                 
        {
                 "title" : "407buskingfb3erhu"
                 "imagename" : "407buskingfb3erhu"
                 "audioname" : "407buskingfb3erhu"
        },
                 
        {
                 "title" : "407buskingsubway1"
                 "imagename" : "407buskingsubway1"
                 "audioname" : "407buskingsubway1"
        },
                 
        {
                 "title" : "407buskingsubway2flute"
                 "imagename" : "407buskingsubway2flute"
                 "audioname" : "407buskingsubway2flute"
        },
                 
        {
                 "title" : "408radio1news"
                 "imagename" : "408radio1news"
                 "audioname" : "408radio1news"
        },
                 
        {
                 "title" : "408radio2show"
                 "imagename" : "408radio2show"
                 "audioname" : "408radio2show"
        },
                 
        {
                 "title" : "408radio3music"
                 "imagename" : "408radio3music"
                 "audioname" : "408radio3music"
        },
    
    ],
    
    "ICSound" : [
                 
        {
                 "title" : ""
                 "imagename" : ""
                 "audioname" : ""
        },
    
    
    ]
    
}
